pysqllike/__init__.py
pysqllike/generic/__init__.py
pysqllike/generic/column_group_operator.py
pysqllike/generic/column_operator.py
pysqllike/generic/column_type.py
pysqllike/generic/iter_exceptions.py
pysqllike/generic/iter_rows.py
pysqllike/generic/others_types.py
pysqllike/translation/__init__.py
pysqllike/translation/code_exception.py
pysqllike/translation/node_visitor_translator.py
pysqllike/translation/translation_class.py
pysqllike/translation/translation_to_python.py
pysqllike-0.1.168.dist-info/DESCRIPTION.rst
pysqllike-0.1.168.dist-info/METADATA
pysqllike-0.1.168.dist-info/RECORD
pysqllike-0.1.168.dist-info/WHEEL
pysqllike-0.1.168.dist-info/metadata.json
pysqllike-0.1.168.dist-info/top_level.txt
