Metadata-Version: 2.0
Name: pysqllike
Version: 0.1.168
Summary: An intent to write SQL like programs and to translate them in Python, SQL, Hive, PIG.
Home-page: http://www.xavierdupre.fr/app/pysqllike/helpsphinx/index.html
Author: Xavier Dupré
Author-email: xavier.dupre@gmail.com
License: MIT
Download-URL: https://github.com/sdpython/pysqllike/
Keywords: pysqllike,SQL,Map Reduce,Xavier,Dupré
Platform: UNKNOWN
Classifier: Programming Language :: Python :: 3
Classifier: Intended Audience :: Developers
Classifier: Topic :: Scientific/Engineering
Classifier: Topic :: Education
Classifier: License :: OSI Approved :: MIT License
Classifier: Development Status :: 5 - Production/Stable
